Metadata-Version: 2.1
Name: check-password
Version: 0.0.2
Summary: lib for check password, email or date for validate
Home-page: https://github.com/pavelglazunov/-check-password-
Author: pavelgs
Author-email: p6282813@yandex.ru
License: Apache License, Version 2.0, see LICENSE file
Platform: UNKNOWN
